cli-conf/GALLERY_HEADER.rst
cli-conf/__init__.py
cli-conf/config.yaml
cli-conf/scenario1-EVI.yaml
cli-conf/scenario1.yaml
cli-conf/scenario2-2d.yaml
cli-conf/scenario2-multi.yaml
cli-conf/scenario2-noise.yaml
cli-conf/scenario2.yaml
cli-conf/scenario3-tpz.yaml
cli-conf/scenario3.yaml
snake/__init__.py
snake/_meta.py
snake/_version.py
snake/core/__init__.py
snake/core/parallel.py
snake/core/simulation.py
snake/core/smaps.py
snake/core/engine/__init__.py
snake/core/engine/base.py
snake/core/engine/cartesian.py
snake/core/engine/nufft.py
snake/core/engine/utils.py
snake/core/handlers/__init__.py
snake/core/handlers/base.py
snake/core/handlers/fov.py
snake/core/handlers/noise.py
snake/core/handlers/utils.py
snake/core/handlers/activations/__init__.py
snake/core/handlers/activations/activations.py
snake/core/handlers/activations/bold.py
snake/core/handlers/activations/roi.py
snake/core/handlers/motion/__init__.py
snake/core/handlers/motion/image.py
snake/core/handlers/motion/utils.py
snake/core/phantom/__init__.py
snake/core/phantom/dynamic.py
snake/core/phantom/shepp_logan.py
snake/core/phantom/static.py
snake/core/phantom/utils.py
snake/core/phantom/data/__init__.py
snake/core/phantom/data/tissues_properties_1T5.csv
snake/core/phantom/data/tissues_properties_7T.csv
snake/core/sampling/__init__.py
snake/core/sampling/base.py
snake/core/sampling/factories.py
snake/core/sampling/samplers.py
snake/mrd_utils/__init__.py
snake/mrd_utils/loader.py
snake/mrd_utils/utils.py
snake/mrd_utils/writer.py
snake/toolkit/__init__.py
snake/toolkit/plotting.py
snake/toolkit/analysis/metrics.py
snake/toolkit/analysis/stats.py
snake/toolkit/cli/__init__.py
snake/toolkit/cli/acquisition.py
snake/toolkit/cli/config.py
snake/toolkit/cli/main.py
snake/toolkit/cli/reconstruction.py
snake/toolkit/reconstructors/__init__.py
snake/toolkit/reconstructors/base.py
snake/toolkit/reconstructors/fourier.py
snake/toolkit/reconstructors/pysap.py
snake_fmri-0.2.0.dist-info/LICENSE.txt
snake_fmri-0.2.0.dist-info/METADATA
snake_fmri-0.2.0.dist-info/WHEEL
snake_fmri-0.2.0.dist-info/entry_points.txt
snake_fmri-0.2.0.dist-info/top_level.txt
snake_fmri-0.2.0.dist-info/RECORD
