Metadata-Version: 2.2
Name: snake-fmri
Version: 0.2.0
Summary: A simulator and validator of fMRI reconstruction methods.
Author-email: Pierre-Antoine Comby <pierre-antoine.comby@cea.fr>
License: Copyright 2023 SNAKE-fMRI Contributors
Project-URL: Homepage, https://github.com/paquiteau/simfmri
Project-URL: Bug Reports, https://github.com/paquiteau/simfmri/issues
Project-URL: Source, https://github.com/paquiteau/simfmri
Keywords: simulation,fMRI
Classifier: Development Status :: 3 - Alpha
Classifier: Intended Audience :: Developers
Classifier: License :: OSI Approved :: MIT License
Classifier: Programming Language :: Python :: 3.10
Classifier: Programming Language :: Python :: 3.11
Classifier: Programming Language :: Python :: 3.12
Requires-Python: >=3.10
License-File: LICENSE.txt
Requires-Dist: numpy
Requires-Dist: scipy
Requires-Dist: nilearn
Requires-Dist: pandas
Requires-Dist: scikit-image
Requires-Dist: brainweb-dl
Requires-Dist: mri-nufft
Requires-Dist: ismrmrd
Requires-Dist: hydra-core
Requires-Dist: hydra-callbacks
Requires-Dist: hydra-colorlog
Provides-Extra: dev
Requires-Dist: black; extra == "dev"
Requires-Dist: ruff; extra == "dev"
Requires-Dist: isort; extra == "dev"
Provides-Extra: test
Requires-Dist: pytest; extra == "test"
Requires-Dist: pytest-cov; extra == "test"
Requires-Dist: pytest-sugar; extra == "test"
Requires-Dist: pytest-xdist; extra == "test"
Provides-Extra: doc
Requires-Dist: myst-parser; extra == "doc"
Requires-Dist: sphinx-copybutton; extra == "doc"
Requires-Dist: sphinx-gallery; extra == "doc"
Requires-Dist: myst-sphinx-gallery; extra == "doc"
Requires-Dist: sphinx-book-theme; extra == "doc"
Requires-Dist: matplotlib; extra == "doc"
Requires-Dist: pysap-fmri; extra == "doc"
Requires-Dist: ipywidgets; extra == "doc"
Requires-Dist: myst-nb; extra == "doc"
Requires-Dist: sphinx-autodoc2; extra == "doc"
Requires-Dist: sphinx-design; extra == "doc"
Requires-Dist: sphinx-tippy; extra == "doc"
Requires-Dist: linkify-it-py; extra == "doc"
Provides-Extra: toolkit
Requires-Dist: matplotlib; extra == "toolkit"
Requires-Dist: pysap-fmri; extra == "toolkit"
